alicelue_brocker_wihtoutapi/__init__.py
alicelue_brocker_wihtoutapi/alice.py
fyers_withoutapi/__init__.py
fyers_withoutapi/fyers.py
fyers_withoutapi-0.0.1.dist-info/LICENSE
fyers_withoutapi-0.0.1.dist-info/METADATA
fyers_withoutapi-0.0.1.dist-info/WHEEL
fyers_withoutapi-0.0.1.dist-info/top_level.txt
fyers_withoutapi-0.0.1.dist-info/RECORD
